{
 "type": "FeatureCollection",
 "generated": "2023-08-22T03:25:53.850857",
 "suburb": "MARREE STATION",
 "features": [
  {
   "type": "Feature",
   "geometry": {
    "type": "Point",
    "coordinates": [
     138.0676721,
     -29.70611318
    ]
   },
   "properties": {
    "name": "LOT 489 THE OUTBACK HIGHWAY MARREE STATION 5733",
    "locID": "EjNUaGUgT3V0YmFjayBId3ksIEZsaW5kZXJzIFJhbmdlcyBTQSA1NDM0LCBBdXN0cmFsaWEiLiosChQKEgldqbcabTKRahFDwUSGbWlPCBIUChIJQeecKnc2lGoRo5oXpT3Mql0",
    "tech": "SATELLITE",
    "upgrade": "UNKNOWN",
    "gnaf_pid": "GASA_425725235"
   }
  }
 ]
}