{
 "type": "FeatureCollection",
 "generated": "2023-07-18T22:49:18.342524",
 "suburb": "NETLEY GAP",
 "features": [
  {
   "type": "Feature",
   "geometry": {
    "type": "Point",
    "coordinates": [
     139.99678823,
     -32.74132835
    ]
   },
   "properties": {
    "name": "1941 NETLEY GAP ROAD NETLEY GAP 5440",
    "locID": "LOC000148245506",
    "tech": "SATELLITE",
    "upgrade": "NULL_NA",
    "gnaf_pid": "GASA_425629806"
   }
  }
 ]
}