{
 "type": "FeatureCollection",
 "generated": "2023-10-02T10:06:46.673559",
 "suburb": "UMBERATANA",
 "features": [
  {
   "type": "Feature",
   "geometry": {
    "type": "Point",
    "coordinates": [
     139.11142165,
     -30.15913036
    ]
   },
   "properties": {
    "name": "5640 UMBERATANA ROAD UMBERATANA 5732",
    "locID": "ChIJhQePZQ9skmoR6jxwv2B12a4",
    "tech": "SATELLITE",
    "upgrade": "UNKNOWN",
    "gnaf_pid": "GASA_425630632"
   }
  }
 ]
}