{
 "type": "FeatureCollection",
 "generated": "2023-08-11T16:21:24.625896",
 "suburb": "PORT STEPHENS",
 "features": [
  {
   "type": "Feature",
   "geometry": {
    "type": "Point",
    "coordinates": [
     152.10485597,
     -32.71711328
    ]
   },
   "properties": {
    "name": "26A CORLETTE POINT ROAD PORT STEPHENS 2317",
    "locID": "ChIJG8CuqiSCc2sRSSMXcd68EQQ",
    "tech": "FTTN",
    "upgrade": "UNKNOWN",
    "gnaf_pid": "GANSW718456526"
   }
  },
  {
   "type": "Feature",
   "geometry": {
    "type": "Point",
    "coordinates": [
     152.01324498,
     -32.66772639
    ]
   },
   "properties": {
    "name": "8 PIER STREET PORT STEPHENS 2317",
    "locID": "ChIJR6kLwVl_c2sRgHu6P2t9ARw",
    "tech": "SATELLITE",
    "upgrade": "UNKNOWN",
    "gnaf_pid": "GANSW719180663"
   }
  },
  {
   "type": "Feature",
   "geometry": {
    "type": "Point",
    "coordinates": [
     151.93912439,
     -32.7343649
    ]
   },
   "properties": {
    "name": "349B MOFFATS ROAD PORT STEPHENS 2317",
    "locID": "ChIJZ6WgaWF6c2sRaaVp3PpDxqY",
    "tech": "WIRELESS",
    "upgrade": "UNKNOWN",
    "gnaf_pid": "GANSW719658529"
   }
  }
 ]
}